bellbird/__init__.py
bellbird/equation.py
bellbird/model.py
bellbird/operators.py
bellbird/variables.py
bellbird/writer.py
bellbird-0.0.1.dist-info/LICENSE
bellbird-0.0.1.dist-info/METADATA
bellbird-0.0.1.dist-info/WHEEL
bellbird-0.0.1.dist-info/top_level.txt
bellbird-0.0.1.dist-info/RECORD
