Metadata-Version: 2.1
Name: bellbird
Version: 0.0.1
Summary: Library that parses differential equations (PDEs) strings and automates the creation of scripts for PyEFVLib using the element-based finite volume method. 
Home-page: https://github.com/GustavoExel/bellbird
Author: Gustavo Exel
Author-email: gustavoexelgpe@gmail.com
License: UNKNOWN
Platform: UNKNOWN
Classifier: Programming Language :: Python :: 3
Classifier: Programming Language :: Python :: 3.6
Classifier: Programming Language :: Python :: 3.7
Classifier: Programming Language :: Python :: 3.8
Classifier: License :: OSI Approved :: MIT License
Classifier: Operating System :: OS Independent
Requires-Dist: numpy (~=1.19.2)
Requires-Dist: PyEFVLib (~=1.0.1)
